LICENSE.txt
MANIFEST.in
README.rst
setup.py
pandas_montecarlo/__init__.py
pandas_montecarlo.egg-info/PKG-INFO
pandas_montecarlo.egg-info/SOURCES.txt
pandas_montecarlo.egg-info/dependency_links.txt
pandas_montecarlo.egg-info/entry_points.txt
pandas_montecarlo.egg-info/requires.txt
pandas_montecarlo.egg-info/top_level.txt