Metadata-Version: 1.1
Name: pandas-montecarlo
Version: 0.0.1
Summary: Monte Carlo Simulator for Pandas
Home-page: https://github.com/ranaroussi/pandas-montecarlo
Author: Ran Aroussi
Author-email: ran@aroussi.com
License: LGPL
Keywords: montecarlo simulator,monte carlo,monte carlo simulation,montecarlo simulation
Platform: any
Classifier: License :: OSI Approved :: GNU Lesser General Public License v3 (LGPLv3)
Classifier: Development Status :: 3 - Alpha
Classifier: Operating System :: OS Independent
Classifier: Intended Audience :: Developers
Classifier: Topic :: Office/Business :: Financial
Classifier: Topic :: Office/Business :: Financial :: Investment
Classifier: Topic :: Scientific/Engineering :: Interface Engine/Protocol Translator
Classifier: Topic :: Software Development :: Libraries
Classifier: Topic :: Software Development :: Libraries :: Python Modules
Classifier: Programming Language :: Python :: 3.4
Classifier: Programming Language :: Python :: 3.5
Classifier: Programming Language :: Python :: 3.6
